mcpcap/__init__.py
mcpcap/_version.py
mcpcap/cli.py
mcpcap/core/__init__.py
mcpcap/core/config.py
mcpcap/core/server.py
mcpcap/modules/__init__.py
mcpcap/modules/base.py
mcpcap/modules/capinfos.py
mcpcap/modules/dhcp.py
mcpcap/modules/dns.py
mcpcap/modules/icmp.py
mcpcap-0.6.0.dist-info/licenses/LICENSE
mcpcap-0.6.0.dist-info/METADATA
mcpcap-0.6.0.dist-info/WHEEL
mcpcap-0.6.0.dist-info/entry_points.txt
mcpcap-0.6.0.dist-info/top_level.txt
mcpcap-0.6.0.dist-info/RECORD
