Metadata-Version: 2.4
Name: mcpcap
Version: 0.6.0
Summary: A modular Python MCP Server for analyzing PCAP files
Author: mcpcap contributors
License: MIT License
Project-URL: Homepage, https://mcpcap.ai
Project-URL: Repository, https://github.com/mcpcap/mcpcap
Project-URL: Issues, https://github.com/mcpcap/mcpcap/issues
Keywords: pcap,network,analysis,mcp,dns
Classifier: Development Status :: 3 - Alpha
Classifier: Intended Audience :: Developers
Classifier: Intended Audience :: System Administrators
Classifier: License :: OSI Approved :: MIT License
Classifier: Programming Language :: Python :: 3
Classifier: Programming Language :: Python :: 3.10
Classifier: Programming Language :: Python :: 3.11
Classifier: Programming Language :: Python :: 3.12
Classifier: Topic :: System :: Networking :: Monitoring
Classifier: Topic :: Security
Requires-Python: >=3.10
License-File: LICENSE
Requires-Dist: fastmcp~=2.12.2
Requires-Dist: scapy~=2.6.1
Requires-Dist: requests~=2.32.5
Provides-Extra: test
Requires-Dist: pytest; extra == "test"
Requires-Dist: pytest-cov; extra == "test"
Requires-Dist: setuptools-scm[toml]; extra == "test"
Provides-Extra: dev
Requires-Dist: setuptools-scm[toml]; extra == "dev"
Requires-Dist: build; extra == "dev"
Requires-Dist: twine; extra == "dev"
Requires-Dist: ruff; extra == "dev"
Requires-Dist: mypy; extra == "dev"
Requires-Dist: pytest; extra == "dev"
Requires-Dist: pytest-cov; extra == "dev"
Provides-Extra: docs
Requires-Dist: sphinx>=7.0; extra == "docs"
Requires-Dist: sphinx-rtd-theme; extra == "docs"
Requires-Dist: myst-parser; extra == "docs"
Requires-Dist: sphinx-autodoc-typehints; extra == "docs"
Requires-Dist: sphinx-copybutton; extra == "docs"
Requires-Dist: linkify-it-py; extra == "docs"
Dynamic: license-file
